[
    {
        "id": 1,
        "nombre": "Cuentas",
        "link": "#",
        "submenu": [
            {
                "id": 11,
                "nombre": "Cuenta de Ahorro",
                "link": "./CuentaAhorro.html",
                "submenu": null
            }
        ]
    },
    {
        "id": 2,
        "nombre": "Inversiones",
        "link": "#",
        "submenu": [
            {
                "id": 21,
                "nombre": "Certificado Financiero",
                "link": "./CertificadoFinanciero.html",
                "submenu": null
            }
        ]
    },

    {
        "id": 3,
        "nombre": "Tarjetas",
        "link": "#",
        "submenu": [
            {
                "id": 31,
                "nombre": "Tarjeta Mastercard",
                "link": "./Mastercard.html",
                "submenu": null
            },

            {
                "id": 32,
                "nombre": "Visa Classic - Mastercard Standard",
                "link": "./VisaMastercard.html",
                "submenu": null
            }
        ]
    },
    {
        "id": 4,
        "nombre": "Prestamos",
        "link": "#",
        "submenu": null
    },
    {
        "id": 5,
        "nombre": "Seguros",
        "link": "#",
        "submenu": null
    },
    {
        "id": 6,
        "nombre": "Remesas, Impuestos y Servicios",
        "link": "#",
        "submenu": null
    },
    {
        "id": 7,
        "nombre": "Cuentas2",
        "link": "#",
        "submenu": [
            {
                "id": 71,
                "nombre": "Cuenta de Ahorro",
                "link": "#",
                "submenu": null
            },
            {
                "id": 72,
                "nombre": "Cuenta de Ahorro2",
                "link": "#",
                "submenu": [{
                    "id": 721,
                    "nombre": "nombre",
                    "link": "#",
                    "submenu": [{
                        "id": 7211,
                        "nombre": "nombre",
                        "link": "#",
                        "submenu": null
                    }]
                }]
            }
        ]
    }
]